Classfile /D:/Work and Projects/Speciale/Soot/Workspace/HelloObfuscator/bin/HelloWorld.class
  Last modified 11-09-2012; size 723 bytes
  MD5 checksum 334bab9a28f995d84227d328334a0643
  Compiled from "HelloWorld.java"
public class HelloWorld
  SourceFile: "HelloWorld.java"
  minor version: 0
  major version: 51
  flags: ACC_PUBLIC, ACC_SUPER¤
Constant pool:
   #1 = Class              #2             //  HelloWorld
   #2 = Utf8               HelloWorld
   #3 = Class              #4             //  java/lang/Object
   #4 = Utf8               java/lang/Object
   #5 = Utf8               foo
   #6 = Utf8               I
   #7 = Utf8               bar
   #8 = Utf8               Ljava/lang/String;
   #9 = Utf8               <init>
  #10 = Utf8               ()V
  #11 = Utf8               Code
  #12 = Methodref          #3.#13         //  java/lang/Object."<init>":()V
  #13 = NameAndType        #9:#10         //  "<init>":()V
  #14 = String             #15            //  3
  #15 = Utf8               3
  #16 = Fieldref           #1.#17         //  HelloWorld.bar:Ljava/lang/String;
  #17 = NameAndType        #7:#8          //  bar:Ljava/lang/String;
  #18 = Utf8               LineNumberTable
  #19 = Utf8               LocalVariableTable
  #20 = Utf8               this
  #21 = Utf8               LHelloWorld;
  #22 = Utf8               Bar
  #23 = Utf8               (I)V
  #24 = Fieldref           #1.#25         //  HelloWorld.foo:I
  #25 = NameAndType        #5:#6          //  foo:I
  #26 = Utf8               i
  #27 = Utf8               StackMapTable
  #28 = Utf8               Foo
  #29 = Utf8               ()I
  #30 = Utf8               j
  #31 = Utf8               SourceFile
  #32 = Utf8               HelloWorld.java
{
  private int foo;
    Signature: I
    flags: ACC_PRIVATE¤


  public java.lang.String bar;
    Signature: Ljava/lang/String;
    flags: ACC_PUBLIC¤


  public HelloWorld();
    Signature: ()V
    flags: ACC_PUBLIC¤
    Code:
      stack=2, locals=1, args_size=1
         0: aload_0       
         1: invokespecial #12                 // Method java/lang/Object."<init>":()V
         4: aload_0       
         5: ldc           #14                 // String 3
         7: putfield      #16                 // Field bar:Ljava/lang/String;
        10: return        
      LineNumberTable:
        line 2: 0
        line 5: 4
        line 2: 10
      LocalVariableTable:
        Start  Length  Slot  Name   Signature
               0      11     0  this   LHelloWorld;

  public void Bar(int);
    Signature: (I)V
    flags: ACC_PUBLIC¤
    Code:
      stack=3, locals=2, args_size=2
         0: aload_0       
         1: bipush        6
         3: iload_1       
         4: iadd          
         5: putfield      #24                 // Field foo:I
         8: aload_0       
         9: getfield      #24                 // Field foo:I
        12: tableswitch   { // 3 to 5
                       3: 40
                       4: 48
                       5: 56
                 default: 65
            }
        40: aload_0       
        41: iconst_4      
        42: putfield      #24                 // Field foo:I
        45: goto          65
        48: aload_0       
        49: iconst_5      
        50: putfield      #24                 // Field foo:I
        53: goto          65
        56: aload_0       
        57: bipush        6
        59: putfield      #24                 // Field foo:I
        62: goto          65
        65: return        
      LineNumberTable:
        line 8: 0
        line 10: 8
        line 12: 40
        line 13: 45
        line 15: 48
        line 16: 53
        line 18: 56
        line 19: 62
        line 24: 65
      LocalVariableTable:
        Start  Length  Slot  Name   Signature
               0      66     0  this   LHelloWorld;
               0      66     1     i   I
      StackMapTable: number_of_entries = 4
           frame_type = 40 /* same */
           frame_type = 7 /* same */
           frame_type = 7 /* same */
           frame_type = 8 /* same */


  public int Foo();
    Signature: ()I
    flags: ACC_PUBLIC¤
    Code:
      stack=2, locals=3, args_size=1
         0: iconst_0      
         1: istore_1      
         2: iconst_0      
         3: istore_2      
         4: goto          14
         7: iload_1       
         8: iload_2       
         9: iadd          
        10: istore_1      
        11: iinc          2, 1
        14: iload_2       
        15: aload_0       
        16: getfield      #24                 // Field foo:I
        19: if_icmplt     7
        22: iload_1       
        23: iconst_5      
        24: if_icmpge     30
        27: bipush        50
        29: ireturn       
        30: iload_1       
        31: ireturn       
      LineNumberTable:
        line 27: 0
        line 28: 2
        line 29: 7
        line 28: 11
        line 32: 22
        line 34: 27
        line 36: 30
      LocalVariableTable:
        Start  Length  Slot  Name   Signature
               0      32     0  this   LHelloWorld;
               2      30     1     j   I
               4      18     2     i   I
      StackMapTable: number_of_entries = 3
           frame_type = 253 /* append */
             offset_delta = 7
        locals = [ int, int ]
           frame_type = 6 /* same */
           frame_type = 250 /* chop */
          offset_delta = 15

}
