Classfile /D:/Work and Projects/Speciale/Soot/Workspace/HelloObfuscator/bin/ClassForByteCode.class
  Last modified 25-10-2012; size 526 bytes
  MD5 checksum fc1fc9ff2b9b8047794c6d8f8792a3dc
  Compiled from "ClassForByteCode.java"
public class ClassForByteCode
  SourceFile: "ClassForByteCode.java"
  minor version: 0
  major version: 51
  flags: ACC_PUBLIC, ACC_SUPER
Constant pool:
   #1 = Class              #2             //  ClassForByteCode
   #2 = Utf8               ClassForByteCode
   #3 = Class              #4             //  java/lang/Object
   #4 = Utf8               java/lang/Object
   #5 = Utf8               <init>
   #6 = Utf8               ()V
   #7 = Utf8               Code
   #8 = Methodref          #3.#9          //  java/lang/Object."<init>":()V
   #9 = NameAndType        #5:#6          //  "<init>":()V
  #10 = Class              #11            //  HelloWorld
  #11 = Utf8               HelloWorld
  #12 = Class              #13            //  "[I"
  #13 = Utf8               [I
  #14 = Class              #15            //  "[[I"
  #15 = Utf8               [[I
  #16 = Class              #17            //  "[[[I"
  #17 = Utf8               [[[I
  #18 = Utf8               LineNumberTable
  #19 = Utf8               LocalVariableTable
  #20 = Utf8               this
  #21 = Utf8               LClassForByteCode;
  #22 = Utf8               iArray
  #23 = Utf8               bArray
  #24 = Utf8               [B
  #25 = Utf8               oArray
  #26 = Utf8               [LHelloWorld;
  #27 = Utf8               diArray
  #28 = Utf8               d2iArray
  #29 = Utf8               d3iArray
  #30 = Utf8               SourceFile
  #31 = Utf8               ClassForByteCode.java
{
  public ClassForByteCode();
    Signature: ()V
    flags: ACC_PUBLIC
    Code:
      stack=3, locals=7, args_size=1
         0: aload_0       
         1: invokespecial #8                  // Method java/lang/Object."<init>":()V
         4: bipush        10
         6: newarray       int
         8: astore_1      
         9: iconst_2      
        10: newarray       byte
        12: astore_2      
        13: iconst_1      
        14: anewarray     #10                 // class HelloWorld
        17: astore_3      
        18: iconst_5      
        19: anewarray     #12                 // class "[I"
        22: astore        4
        24: bipush        6
        26: bipush        7
        28: multianewarray #14,  2            // class "[[I"
        32: astore        5
        34: bipush        6
        36: bipush        7
        38: bipush        8
        40: multianewarray #16,  3            // class "[[[I"
        44: astore        6
        46: return        
      LineNumberTable:
        line 4: 0
        line 5: 4
        line 6: 9
        line 7: 13
        line 8: 18
        line 9: 24
        line 10: 34
        line 11: 46
      LocalVariableTable:
        Start  Length  Slot  Name   Signature
               0      47     0  this   LClassForByteCode;
               9      38     1 iArray   [I
              13      34     2 bArray   [B
              18      29     3 oArray   [LHelloWorld;
              24      23     4 diArray   [[I
              34      13     5 d2iArray   [[I
              46       1     6 d3iArray   [[[I
}
